[
  {
    "name": "BillGates",
    "viewers": "388",
    "avatar": "https://laverdadnoticias.com/export/sites/laverdad/img/2021/04/21/bill_gates.jpg_2064564707.jpg",
    "game": "Terraria",
    "tags": ["Español", "Chino"]
  },
  {
    "name": "SteveJobs",
    "viewers": "240",
    "avatar": "https://encrypted-tbn0.gstatic.com/images?q=tbn:ANd9GcRijkzWWcAPqtTMIdFL3GhkVAXKSsBSQeeXng&usqp=CAU",
    "game": "Just Chatting",
    "tags": ["Inglés", "Portugués"]
  },
  {
    "name": "JeffBezos",
    "viewers": "4.2k",
    "avatar": "http://cdn2.dineroenimagen.com/media/dinero/jeff-bezos.jpeg",
    "game": "Roblox",
    "tags": ["Inglés", "Español"]
  },
  {
    "name": "ElonMusk",
    "viewers": "10",
    "avatar": "https://cachedimages.podchaser.com/256x256/aHR0cHM6Ly9jcmVhdG9yLWltYWdlcy5wb2RjaGFzZXIuY29tL2RmODZjM2RjZTg5ZDI2ZGQzZWI5NWU4YzI1MDBhMTIyLmpwZWc%3D/aHR0cHM6Ly93d3cucG9kY2hhc2VyLmNvbS9pbWFnZXMvbWlzc2luZy1pbWFnZS5wbmc%3D",
    "game": "Minecraft",
    "tags": ["Italiano"]
  },
  {
    "name": "MarkZuckerberg",
    "viewers": "38",
    "avatar": "https://pbs.twimg.com/profile_images/730271326150103042/gR9RVbmC_400x400.jpg",
    "game": "Fortnite",
    "tags": ["Inglés"]
  }
]
